pager_cli/__init__.py
pager_cli/__main__.py
pager_cli/cli.py
pager_cli/tests/__init__.py
pager_cli/tests/conftest.py
pager_cli-0.2.dist-info/entry_points.txt
pager_cli-0.2.dist-info/LICENSE.md
pager_cli-0.2.dist-info/WHEEL
pager_cli-0.2.dist-info/METADATA
pager_cli-0.2.dist-info/RECORD
