Metadata-Version: 2.1
Name: pager-cli
Version: 0.2
Summary: pagerduty cli to list/ack/resolve incidents
Home-page: https://pypi.org/project/pager_cli
License: MIT
Author: Frankie
Author-email: f@peering.sh
Requires-Python: >=3.7,<4.0
Classifier: Development Status :: 1 - Planning
Classifier: License :: OSI Approved :: MIT License
Classifier: Natural Language :: English
Classifier: Operating System :: OS Independent
Classifier: Programming Language :: Python
Classifier: Programming Language :: Python :: 3
Classifier: Programming Language :: Python :: 3.7
Classifier: Programming Language :: Python :: 3.8
Classifier: Programming Language :: Python :: 3.9
Requires-Dist: click (>=7.0,<8.0)
Requires-Dist: minilog (>=2.0,<3.0)
Requires-Dist: requests (>=2.25.1,<3.0.0)
Requires-Dist: requests-mock (>=1.9.3,<2.0.0)
Requires-Dist: strictyaml (>=1.4.4,<2.0.0)
Requires-Dist: tabulate (>=0.8.9,<0.9.0)
Requires-Dist: types-requests (>=2.25.0,<3.0.0)
Requires-Dist: types-setuptools (>=57.0.0,<58.0.0)
Requires-Dist: types-tabulate (>=0.1.1,<0.2.0)
Requires-Dist: yaspin (>=2.0.0,<3.0.0)
Project-URL: Documentation, https://pager_cli.readthedocs.io
Project-URL: Repository, https://github.com/frankiexyz/pager_cli
